README.md
setup.py
libpythonproh/__init__.py
libpythonproh/github_api.py
libpythonproh.egg-info/PKG-INFO
libpythonproh.egg-info/SOURCES.txt
libpythonproh.egg-info/dependency_links.txt
libpythonproh.egg-info/not-zip-safe
libpythonproh.egg-info/requires.txt
libpythonproh.egg-info/top_level.txt
libpythonproh/spam/__init__.py
libpythonproh/spam/db.py
libpythonproh/spam/enviador_de_email.py
libpythonproh/spam/main.py
libpythonproh/spam/modelos.py
libpythonproh/tests/__init__.py
libpythonproh/tests/test_exemplo.py
libpythonproh/tests/test_spam/__init__.py
libpythonproh/tests/test_spam/conftest.py
libpythonproh/tests/test_spam/test_enviador_de_email.py
libpythonproh/tests/test_spam/test_envio_para_base_de_usuarios.py
libpythonproh/tests/test_spam/test_usuarios.py