Metadata-Version: 2.1
Name: libpythonproh
Version: 0.3
Summary: Treinamentos diversos em Python para aprender algumas ferramentas em python.
Home-page: https://github.com/herminiojunior/treinamento
Author: Herminio Junior
Author-email: email@gmail.com
License: UNKNOWN
Platform: UNKNOWN
Classifier: Development Status :: 2 - Pre-Alpha
Classifier: Environment :: Console
Classifier: Intended Audience :: Developers
Classifier: License :: OSI Approved :: GNU Affero General Public License v3 or later (AGPLv3+)
Classifier: Operating System :: OS Independent
Classifier: Programming Language :: Python :: 3.7
Classifier: Framework :: Pytest
